struct2block/__init__.py
struct2block/struct2block.py
struct2block/data/van_der_Waals_Radii.csv
struct2block-1.1.dist-info/METADATA
struct2block-1.1.dist-info/WHEEL
struct2block-1.1.dist-info/entry_points.txt
struct2block-1.1.dist-info/licenses/LICENSE
struct2block-1.1.dist-info/RECORD
