Metadata-Version: 2.4
Name: struct2block
Version: 1.1
Summary: Detect functional block of protein. If you have two different proteins that bind to the same target protein. Struct2Block is an easy tool designed for quickly evaluating the following situations:1) An antibody binds to a receptor. To what extent does it sterically hinder the ligand. 2)2 different ligands bind to the same receptor. To what degree does they compete.
Project-URL: Homepage, https://github.com/Chou-Uken/struct2block
Project-URL: Issues, https://github.com/Chou-Uken/struct2block/issues
Author: Zhang Yujian
Maintainer: Zhang Yujian
License-Expression: Apache-2.0
License-File: LICENSE
Classifier: Operating System :: OS Independent
Classifier: Programming Language :: Python :: 3
Requires-Python: >=3.9
Requires-Dist: biotite>=1.3
Requires-Dist: numpy>=2.3.1
Requires-Dist: typer>=0.16
